romitask/__init__.py
romitask/log.py
romitask/modules.py
romitask/runner.py
romitask/task.py
romitask/utils.py
romitask/watch.py
romitask/cli/__init__.py
romitask/cli/print_task_info.py
romitask/cli/romi_run_task.py
romitask-0.12.1.dist-info/licenses/LICENSE
romitask-0.12.1.dist-info/METADATA
romitask-0.12.1.dist-info/WHEEL
romitask-0.12.1.dist-info/entry_points.txt
romitask-0.12.1.dist-info/top_level.txt
romitask-0.12.1.dist-info/RECORD
