Metadata-Version: 2.4
Name: romitask
Version: 0.12.1
Summary: The ROMI task runner, a luigi based task pipeline.
Author-email: Peter Hanappe <peter.hanappe@sony.com>, Timothée Wintz <timothee@timwin.fr>, Nabil Ait Taleb <mohamednabil.aittaleb@sony.com>
Maintainer-email: Jonathan Legrand <jonathan.legrand@ens-lyon.fr>
License: LGPL-3.0-or-later
Project-URL: homepage, https://romi-project.eu/
Project-URL: documentation, https://docs.romi-project.eu/plant_imager/
Project-URL: source, https://github.com/romi/romitask
Project-URL: issues, https://github.com/romi/romitask/issues
Keywords: Robotics for Microfarms,ROMI,Runner,Luigi,Pipeline
Classifier: Programming Language :: Python :: 3
Classifier: Development Status :: 4 - Beta
Classifier: Intended Audience :: Science/Research
Classifier: Topic :: Scientific/Engineering :: Bio-Informatics
Classifier: Topic :: Software Development :: Libraries :: Python Modules
Classifier: Operating System :: OS Independent
Classifier: Natural Language :: English
Requires-Python: >=3.8
License-File: LICENSE
Requires-Dist: numpy
Requires-Dist: colorlog
Requires-Dist: luigi
Requires-Dist: toml
Requires-Dist: tqdm
Requires-Dist: watchdog
Provides-Extra: doc
Requires-Dist: mkdocs; extra == "doc"
Requires-Dist: mkdocs-material; extra == "doc"
Requires-Dist: mkdocstrings[python]; extra == "doc"
Requires-Dist: pymdown-extensions; extra == "doc"
Requires-Dist: markdown-exec[ansi]; extra == "doc"
Dynamic: license-file
